programcounter.v
	/*
	************ 4-BIT COUNTER *************
     	* works in sync with a clock(clk)
	* inputs: accepts a 4 bit binary value
	* outputs: outputs a 4 bit binary value
	* control signals: 
		* clear(clr): Resets the value of the counter to 0x00
		* output enable(oe):Outputs the value of counter on output line
		* jump(jmp):Latches in value set on input lines
		* increment(inc):Increments the value in counter  
*/
       module counter(
		output[0:3] out,
		input[0:3] in,
		input clk,clr,oe,jmp,inc);
	reg[0:3] store; 

//	assign out=(oe && clk)?store:8'bxxxxxxxx;	
	always @(posedge clk)
	begin
		if(clr)
			store<=4'b0;
		else if(jmp)
			store<=in;
		else if(inc)
                        store<=store+1;
//		if(oe)
//			out<=store;
	end
	
	assign out=oe?store:4'bzzzz;
/*	always @(posedge clk)
		case(oe)
			1: out<=store;
		       default: out<=4'bzzzz;
	       endcase	       
*/	endmodule

testcounter.v
	`timescale 10ns/1ns
	module test;
	wire[3:0] out;
	reg[3:0] in;
	reg clr,oe,jmp,inc,clk;
	counter ctr(out,in,clk,clr,oe,jmp,inc);
	
	initial begin
		clk=0;oe=0;jmp=0;inc=0;
       	end

	always	#1 clk=~clk;

	initial
	begin
		clr=1;
		#2 clr=0;oe=1;in=4'b1100;
		#2 inc=1;in=4'b1010;
		#4 inc=0;jmp=1;
		#4 $finish;
	end
	initial
	begin
		$monitor($time,"	clr=%b	oe=%b	jmp=%b	inc=%b	in=%h	out=%h store=%h",clr,oe,jmp,inc,in,out,ctr.store);
		$dumpfile("vars.vcd");
		$dumpvars(0,test);
	end
	endmodule

vars.vcd
$date
	Thu Sep 17 19:52:30 2020
$end
$version
	Icarus Verilog
$end
$timescale
	1ns
$end
$scope module test $end
$var wire 4 ! out [0:3] $end
$var reg 1 " clk $end
$var reg 1 # clr $end
$var reg 4 $ in [0:3] $end
$var reg 1 % inc $end
$var reg 1 & jmp $end
$var reg 1 ' oe $end
$scope module ctr $end
$var wire 1 " clk $end
$var wire 1 # clr $end
$var wire 4 ( in [0:3] $end
$var wire 1 % inc $end
$var wire 1 & jmp $end
$var wire 1 ' oe $end
$var wire 4 ) out [0:3] $end
$var reg 4 * store [0:3] $end
$upscope $end
$upscope $end
$enddefinitions $end
#0
$dumpvars
bx *
bz )
bx (
0'
0&
0%
bx $
1#
0"
bz !
$end
#10
b0 *
1"
#20
b0 !
b0 )
0"
b1100 $
b1100 (
1'
0#
#30
1"
#40
0"
b1010 $
b1010 (
1%
#50
b1 !
b1 )
b1 *
1"
#60
0"
#70
b10 !
b10 )
b10 *
1"
#80
0"
1&
0%
#90
b1010 !
b1010 )
b1010 *
1"
